swiftly_api_client/__init__.py
swiftly_api_client/__version__.py
swiftly_api_client/network.py
swiftly_api_python_client-0.17.0.dist-info/METADATA
swiftly_api_python_client-0.17.0.dist-info/WHEEL
swiftly_api_python_client-0.17.0.dist-info/top_level.txt
swiftly_api_python_client-0.17.0.dist-info/RECORD
