Metadata-Version: 2.4
Name: swiftly_api_python_client
Version: 0.17.0
Summary: Hopthru's Swiftly API Python Client
Home-page: https://github.com/Hopthru/swiftly-api-python-client
Author: Swiftly
Author-email: brock@goswift.ly
Classifier: Programming Language :: Python :: 3
Classifier: License :: OSI Approved :: MIT License
Classifier: Operating System :: OS Independent
Requires-Python: >=3.10
Requires-Dist: pandas>=1.5.3
Requires-Dist: typing-extensions>=3.10
Requires-Dist: requests>=2.28
